saltedmd5/__init__.py
saltedmd5/saltedmd5.py
saltedmd5/test_saltedmd5.py
saltedmd5-1.0.7.dist-info/LICENSE
saltedmd5-1.0.7.dist-info/METADATA
saltedmd5-1.0.7.dist-info/WHEEL
saltedmd5-1.0.7.dist-info/top_level.txt
saltedmd5-1.0.7.dist-info/RECORD
