Metadata-Version: 2.1
Name: saltedmd5
Version: 1.0.7
Summary: saltedmd5 is a python package for performing md5 hashing with salt.
Home-page: https://github.com/nat236919/saltedmd5
Author: Nuttaphat Arunoprayoch
Author-email: nat236919@gmail.com
License: MIT
Platform: UNKNOWN
Classifier: Development Status :: 5 - Production/Stable
Classifier: License :: OSI Approved :: MIT License
Classifier: Programming Language :: Python
Classifier: Topic :: Software Development :: Libraries
Classifier: Topic :: Software Development :: Libraries :: Python Modules
Classifier: Intended Audience :: Developers
Classifier: Intended Audience :: End Users/Desktop
Requires-Python: >=3.5
